keymaster_sdk/__init__.py
keymaster_sdk/keymaster_sdk.py
keymaster_sdk-1.2.1.dist-info/licenses/LICENSE
keymaster_sdk-1.2.1.dist-info/METADATA
keymaster_sdk-1.2.1.dist-info/WHEEL
keymaster_sdk-1.2.1.dist-info/top_level.txt
keymaster_sdk-1.2.1.dist-info/RECORD
