Metadata-Version: 2.4
Name: keymaster-sdk
Version: 1.2.1
Summary: Keymaster is a client library for the MDIP
Author-email: David McFadzean <david@selfid.com>, Peter Bushnell <peter@selfid.com>
License: MIT License
Project-URL: Homepage, https://github.com/KeychainMDIP/kc/
License-File: LICENSE
Requires-Dist: requests==2.32.0
Dynamic: license-file
